[
  {
    "title": "The myth of reflected power (2017)",
    "link": "https://www.iz2uuf.net/wp/index.php/2017/07/29/the-myth-of-reflected-power/",
    "source": "Hacker News",
    "published": "2025-11-26T03:05:29+00:00",
    "author": "Hacker News",
    "summary": "<a href=\"https://news.ycombinator.com/item?id=46053787\">Comments</a>"
  },
  {
    "title": "Space Truckin' \u2013 The Nostromo (2012)",
    "link": "https://alienseries.wordpress.com/2012/10/23/space-truckin-the-nostromo/",
    "source": "Hacker News",
    "published": "2025-11-26T02:31:41+00:00",
    "author": "Hacker News",
    "summary": "<a href=\"https://news.ycombinator.com/item?id=46053566\">Comments</a>"
  },
  {
    "title": "BebboSSH: SSH2 implementation for Amiga systems (68000, GPLv3)",
    "link": "https://franke.ms/git/bebbo/bebbossh",
    "source": "Hacker News",
    "published": "2025-11-26T01:51:26+00:00",
    "author": "Hacker News",
    "summary": "<a href=\"https://news.ycombinator.com/item?id=46053262\">Comments</a>"
  },
  {
    "title": "CS234: Reinforcement Learning Winter 2025",
    "link": "https://web.stanford.edu/class/cs234/",
    "source": "Hacker News",
    "published": "2025-11-26T00:33:29+00:00",
    "author": "Hacker News",
    "summary": "<a href=\"https://news.ycombinator.com/item?id=46052685\">Comments</a>"
  },
  {
    "title": "Show HN: KiDoom \u2013 Running DOOM on PCB Traces",
    "link": "https://www.mikeayles.com/#kidoom",
    "source": "Hacker News",
    "published": "2025-11-25T22:13:35+00:00",
    "author": "Hacker News",
    "summary": "<a href=\"https://news.ycombinator.com/item?id=46051449\">Comments</a>"
  },
  {
    "title": "A new bridge links the math of infinity to computer science",
    "link": "https://www.quantamagazine.org/a-new-bridge-links-the-strange-math-of-infinity-to-computer-science-20251121/",
    "source": "Hacker News",
    "published": "2025-11-25T19:53:20+00:00",
    "author": "Hacker News",
    "summary": "<a href=\"https://news.ycombinator.com/item?id=46049932\">Comments</a>"
  },
  {
    "title": "The Bughouse Effect",
    "link": "https://tsvibt.blogspot.com/2025/11/the-bughouse-effect.html",
    "source": "Hacker News",
    "published": "2025-11-25T19:43:42+00:00",
    "author": "Hacker News",
    "summary": "<a href=\"https://news.ycombinator.com/item?id=46049835\">Comments</a>"
  },
  {
    "title": "Google Antigravity exfiltrates data via indirect prompt injection attack",
    "link": "https://www.promptarmor.com/resources/google-antigravity-exfiltrates-data",
    "source": "Hacker News",
    "published": "2025-11-25T18:31:16+00:00",
    "author": "Hacker News",
    "summary": "<a href=\"https://news.ycombinator.com/item?id=46048996\">Comments</a>"
  },
  {
    "title": "Show HN: We built an open source, zero webhooks payment processor",
    "link": "https://github.com/flowglad/flowglad",
    "source": "Hacker News",
    "published": "2025-11-25T17:33:50+00:00",
    "author": "Hacker News",
    "summary": "<a href=\"https://news.ycombinator.com/item?id=46048252\">Comments</a>"
  },
  {
    "title": "Ilya Sutskever: We're moving from the age of scaling to the age of research",
    "link": "https://www.dwarkesh.com/p/ilya-sutskever-2",
    "source": "Hacker News",
    "published": "2025-11-25T17:21:52+00:00",
    "author": "Hacker News",
    "summary": "<a href=\"https://news.ycombinator.com/item?id=46048125\">Comments</a>"
  },
  {
    "title": "New layouts with CSS Subgrid",
    "link": "https://www.joshwcomeau.com/css/subgrid/",
    "source": "Hacker News",
    "published": "2025-11-25T15:57:54+00:00",
    "author": "Hacker News",
    "summary": "<a href=\"https://news.ycombinator.com/item?id=46047053\">Comments</a>"
  },
  {
    "title": "FLUX.2: Frontier Visual Intelligence",
    "link": "https://bfl.ai/blog/flux-2",
    "source": "Hacker News",
    "published": "2025-11-25T15:47:14+00:00",
    "author": "Hacker News",
    "summary": "<a href=\"https://news.ycombinator.com/item?id=46046916\">Comments</a>"
  },
  {
    "title": "Launch HN: Onyx (YC W24) \u2013 Open-source chat UI",
    "link": "https://news.ycombinator.com/item?id=46045987",
    "source": "Hacker News",
    "published": "2025-11-25T14:20:30+00:00",
    "author": "Hacker News",
    "summary": "<a href=\"https://news.ycombinator.com/item?id=46045987\">Comments</a>"
  },
  {
    "title": "Trillions spent and big software projects are still failing",
    "link": "https://spectrum.ieee.org/it-management-software-failures",
    "source": "Hacker News",
    "published": "2025-11-25T12:14:11+00:00",
    "author": "Hacker News",
    "summary": "<a href=\"https://news.ycombinator.com/item?id=46045085\">Comments</a>"
  },
  {
    "title": "1,700-year-old Roman sarcophagus is unearthed in Budapest",
    "link": "https://apnews.com/article/hungary-roman-sarcophagus-discovery-budapest-77a41fe190bbcc167b43d05141536f54",
    "source": "Hacker News",
    "published": "2025-11-24T22:17:40+00:00",
    "author": "Hacker News",
    "summary": "<a href=\"https://news.ycombinator.com/item?id=46040053\">Comments</a>"
  },
  {
    "title": "Surprisingly, Emacs on Android is pretty good",
    "link": "https://kristofferbalintona.me/posts/202505291438/",
    "source": "Hacker News",
    "published": "2025-11-23T07:40:26+00:00",
    "author": "Hacker News",
    "summary": "<a href=\"https://news.ycombinator.com/item?id=46021577\">Comments</a>"
  },
  {
    "title": "How to repurpose your old phone into a web server",
    "link": "https://far.computer/how-to/",
    "source": "Hacker News",
    "published": "2025-11-22T18:16:59+00:00",
    "author": "Hacker News",
    "summary": "<a href=\"https://news.ycombinator.com/item?id=46016902\">Comments</a>"
  },
  {
    "title": "Java Decompiler",
    "link": "http://java-decompiler.github.io",
    "source": "Hacker News",
    "published": "2025-11-22T17:44:12+00:00",
    "author": "Hacker News",
    "summary": "<a href=\"https://news.ycombinator.com/item?id=46016579\">Comments</a>"
  },
  {
    "title": "First Air-Breathing Spacecraft",
    "link": "https://rdw.com/newsroom/redwire-awarded-44-million-darpa-contract-to-advance-very-low-earth-orbit-mission/",
    "source": "Hacker News",
    "published": "2025-11-20T16:17:09+00:00",
    "author": "Hacker News",
    "summary": "<a href=\"https://news.ycombinator.com/item?id=45994277\">Comments</a>"
  },
  {
    "title": "Marble Springs (1993)",
    "link": "https://www.eastgate.com/MS/Title_184.html",
    "source": "Hacker News",
    "published": "2025-11-20T07:33:38+00:00",
    "author": "Hacker News",
    "summary": "<a href=\"https://news.ycombinator.com/item?id=45989947\">Comments</a>"
  }
]