[
  {
    "title": "Iran Protest Death Toll Could Top 30k, According to Local Health Officials",
    "link": "https://time.com/7357635/more-than-30000-killed-in-iran-say-senior-officials/",
    "source": "Hacker News",
    "published": "2026-01-25T13:59:42+00:00",
    "author": "Hacker News",
    "summary": "<a href=\"https://news.ycombinator.com/item?id=46754132\">Comments</a>"
  },
  {
    "title": "Web-based image editor modeled after Deluxe Paint",
    "link": "https://github.com/steffest/DPaint-js",
    "source": "Hacker News",
    "published": "2026-01-25T12:54:53+00:00",
    "author": "Hacker News",
    "summary": "<a href=\"https://news.ycombinator.com/item?id=46753708\">Comments</a>"
  },
  {
    "title": "Alarm overload is undermining safety at sea as crews face thousands of alerts",
    "link": "https://www.lr.org/en/knowledge/press-room/press-listing/press-release/2026/alarm-overload-is-undermining-safety-at-sea-as-new-research-shows-crews-face-tens-of-thousands-of-daily-alerts/",
    "source": "Hacker News",
    "published": "2026-01-25T12:40:00+00:00",
    "author": "Hacker News",
    "summary": "<a href=\"https://news.ycombinator.com/item?id=46753611\">Comments</a>"
  },
  {
    "title": "Doom has been ported to an earbud",
    "link": "https://doombuds.com",
    "source": "Hacker News",
    "published": "2026-01-25T12:22:12+00:00",
    "author": "Hacker News",
    "summary": "<a href=\"https://news.ycombinator.com/item?id=46753484\">Comments</a>"
  },
  {
    "title": "Nango (YC W23, Dev Infrastructure) Is Hiring Remotely",
    "link": "https://jobs.ashbyhq.com/Nango",
    "source": "Hacker News",
    "published": "2026-01-25T12:02:01+00:00",
    "author": "Hacker News",
    "summary": "<a href=\"https://news.ycombinator.com/item?id=46753336\">Comments</a>"
  },
  {
    "title": "Show HN: Bonsplit \u2013 Tabs and splits for native macOS apps",
    "link": "https://bonsplit.alasdairmonk.com",
    "source": "Hacker News",
    "published": "2026-01-25T11:56:42+00:00",
    "author": "Hacker News",
    "summary": "<a href=\"https://news.ycombinator.com/item?id=46753301\">Comments</a>"
  },
  {
    "title": "Show HN: TUI for managing XDG default applications",
    "link": "https://github.com/mitjafelicijan/xdgctl",
    "source": "Hacker News",
    "published": "2026-01-25T11:19:04+00:00",
    "author": "Hacker News",
    "summary": "<a href=\"https://news.ycombinator.com/item?id=46753078\">Comments</a>"
  },
  {
    "title": "Bridging the Gap Between PLECS and SPICE",
    "link": "https://erickschulz.dev/posts/plecs-spice/",
    "source": "Hacker News",
    "published": "2026-01-25T10:44:08+00:00",
    "author": "Hacker News",
    "summary": "<a href=\"https://news.ycombinator.com/item?id=46752841\">Comments</a>"
  },
  {
    "title": "Jurassic Park - Tablet device on Nedry's desk? (2012)",
    "link": "https://www.therpf.com/forums/threads/jurassic-park-tablet-device-on-nedrys-desk.169883/",
    "source": "Hacker News",
    "published": "2026-01-25T09:22:17+00:00",
    "author": "Hacker News",
    "summary": "<a href=\"https://news.ycombinator.com/item?id=46752261\">Comments</a>"
  },
  {
    "title": "This paper has been cited more than 6k times. It's fatally flawed.",
    "link": "https://statmodeling.stat.columbia.edu/2026/01/22/aking/",
    "source": "Hacker News",
    "published": "2026-01-25T09:04:30+00:00",
    "author": "Hacker News",
    "summary": "<a href=\"https://news.ycombinator.com/item?id=46752151\">Comments</a>"
  },
  {
    "title": "Deutsche Telekom is violating Net Neutrality",
    "link": "https://netzbremse.de/en/",
    "source": "Hacker News",
    "published": "2026-01-25T08:22:17+00:00",
    "author": "Hacker News",
    "summary": "<a href=\"https://news.ycombinator.com/item?id=46751899\">Comments</a>"
  },
  {
    "title": "Introduction to PostgreSQL Indexes",
    "link": "https://dlt.github.io/blog/posts/introduction-to-postgresql-indexes/",
    "source": "Hacker News",
    "published": "2026-01-25T08:07:03+00:00",
    "author": "Hacker News",
    "summary": "<a href=\"https://news.ycombinator.com/item?id=46751826\">Comments</a>"
  },
  {
    "title": "Adoption of EVs tied to real-world reductions in air pollution: study",
    "link": "https://keck.usc.edu/news/adoption-of-electric-vehicles-tied-to-real-world-reductions-in-air-pollution-study-finds/",
    "source": "Hacker News",
    "published": "2026-01-25T00:14:40+00:00",
    "author": "Hacker News",
    "summary": "<a href=\"https://news.ycombinator.com/item?id=46749198\">Comments</a>"
  },
  {
    "title": "BirdyChat becomes first European chat app that is interoperable with WhatsApp",
    "link": "https://www.birdy.chat/blog/first-to-interoperate-with-whatsapp",
    "source": "Hacker News",
    "published": "2026-01-24T19:04:08+00:00",
    "author": "Hacker News",
    "summary": "<a href=\"https://news.ycombinator.com/item?id=46746476\">Comments</a>"
  },
  {
    "title": "BU-808: How to Prolong Lithium-based Batteries (2023)",
    "link": "https://www.batteryuniversity.com/article/bu-808-how-to-prolong-lithium-based-batteries/",
    "source": "Hacker News",
    "published": "2026-01-23T06:34:31+00:00",
    "author": "Hacker News",
    "summary": "<a href=\"https://news.ycombinator.com/item?id=46729198\">Comments</a>"
  },
  {
    "title": "ANN v3: 200ms p99 query latency over 100B vectors",
    "link": "https://turbopuffer.com/blog/ann-v3",
    "source": "Hacker News",
    "published": "2026-01-21T19:58:59+00:00",
    "author": "Hacker News",
    "summary": "<a href=\"https://news.ycombinator.com/item?id=46710747\">Comments</a>"
  },
  {
    "title": "A Lament for Aperture",
    "link": "https://ikennd.ac/blog/2026/01/old-man-yells-at-modern-software-design/",
    "source": "Hacker News",
    "published": "2026-01-21T00:35:01+00:00",
    "author": "Hacker News",
    "summary": "<a href=\"https://news.ycombinator.com/item?id=46699697\">Comments</a>"
  },
  {
    "title": "I built a 2x faster lexer, then discovered I/O was the real bottleneck",
    "link": "https://modulovalue.com/blog/syscall-overhead-tar-gz-io-performance/",
    "source": "Hacker News",
    "published": "2026-01-20T16:10:01+00:00",
    "author": "Hacker News",
    "summary": "<a href=\"https://news.ycombinator.com/item?id=46693460\">Comments</a>"
  },
  {
    "title": "Google confirms 'high-friction' sideloading flow is coming to Android",
    "link": "https://www.androidauthority.com/google-sideloading-android-high-friction-process-3633468/",
    "source": "Hacker News",
    "published": "2026-01-20T07:04:53+00:00",
    "author": "Hacker News",
    "summary": "<a href=\"https://news.ycombinator.com/item?id=46688804\">Comments</a>"
  },
  {
    "title": "The Rebirth of Pennsylvania's Infamous Burning Town",
    "link": "https://www.atlasobscura.com/articles/centralia-pennsylvania-rebirth",
    "source": "Hacker News",
    "published": "2026-01-20T06:10:54+00:00",
    "author": "Hacker News",
    "summary": "<a href=\"https://news.ycombinator.com/item?id=46688476\">Comments</a>"
  }
]