[
  {
    "title": "Rocket Lab \u2013 'Raise and Shine' Launch for JAXA [video]",
    "link": "https://www.youtube.com/watch?v=cMP328yoUu4",
    "source": "Hacker News",
    "published": "2025-12-14T03:13:38+00:00",
    "author": "Hacker News",
    "summary": "<a href=\"https://news.ycombinator.com/item?id=46260474\">Comments</a>"
  },
  {
    "title": "Lean Theorem Prover Mathlib",
    "link": "https://github.com/leanprover-community/mathlib4",
    "source": "Hacker News",
    "published": "2025-12-14T01:49:11+00:00",
    "author": "Hacker News",
    "summary": "<a href=\"https://news.ycombinator.com/item?id=46260128\">Comments</a>"
  },
  {
    "title": "Therapeutic Use of Cannabis and Cannabinoids: A Review",
    "link": "https://jamanetwork.com/journals/jama/fullarticle/2842072?guestAccessKey=a368e622-e374-4a0c-8d3b-22a976500305",
    "source": "Hacker News",
    "published": "2025-12-14T01:32:36+00:00",
    "author": "Hacker News",
    "summary": "<a href=\"https://news.ycombinator.com/item?id=46260039\">Comments</a>"
  },
  {
    "title": "Free Software Awards Winners Announced: Andy Wingo, Alx Sa, Govdirectory",
    "link": "https://www.fsf.org/news/2024-free-software-awards-winners",
    "source": "Hacker News",
    "published": "2025-12-14T01:19:50+00:00",
    "author": "Hacker News",
    "summary": "<a href=\"https://news.ycombinator.com/item?id=46259970\">Comments</a>"
  },
  {
    "title": "Awesome-Jj: Jujutsu Things",
    "link": "https://github.com/Necior/awesome-jj",
    "source": "Hacker News",
    "published": "2025-12-14T01:10:11+00:00",
    "author": "Hacker News",
    "summary": "<a href=\"https://news.ycombinator.com/item?id=46259914\">Comments</a>"
  },
  {
    "title": "An Implementation of J",
    "link": "https://www.jsoftware.com/ioj/ioj.htm",
    "source": "Hacker News",
    "published": "2025-12-14T00:34:56+00:00",
    "author": "Hacker News",
    "summary": "<a href=\"https://news.ycombinator.com/item?id=46259702\">Comments</a>"
  },
  {
    "title": "Closures as Win32 Window Procedures",
    "link": "https://nullprogram.com/blog/2025/12/12/",
    "source": "Hacker News",
    "published": "2025-12-13T23:39:48+00:00",
    "author": "Hacker News",
    "summary": "<a href=\"https://news.ycombinator.com/item?id=46259334\">Comments</a>"
  },
  {
    "title": "Linux Sandboxes and Fil-C",
    "link": "https://fil-c.org/seccomp",
    "source": "Hacker News",
    "published": "2025-12-13T22:58:29+00:00",
    "author": "Hacker News",
    "summary": "<a href=\"https://news.ycombinator.com/item?id=46259064\">Comments</a>"
  },
  {
    "title": "Recovering Anthony Bourdain's (really) lost Li.st's",
    "link": "https://sandyuraz.com/blogs/bourdain/",
    "source": "Hacker News",
    "published": "2025-12-13T21:18:01+00:00",
    "author": "Hacker News",
    "summary": "<a href=\"https://news.ycombinator.com/item?id=46258163\">Comments</a>"
  },
  {
    "title": "Why Twilio Segment moved from microservices back to a monolith",
    "link": "https://www.twilio.com/en-us/blog/developers/best-practices/goodbye-microservices",
    "source": "Hacker News",
    "published": "2025-12-13T20:30:34+00:00",
    "author": "Hacker News",
    "summary": "<a href=\"https://news.ycombinator.com/item?id=46257714\">Comments</a>"
  },
  {
    "title": "I fed 24 years of my blog posts to a Markov model",
    "link": "https://susam.net/fed-24-years-of-posts-to-markov-model.html",
    "source": "Hacker News",
    "published": "2025-12-13T20:19:53+00:00",
    "author": "Hacker News",
    "summary": "<a href=\"https://news.ycombinator.com/item?id=46257607\">Comments</a>"
  },
  {
    "title": "The Rise of Computer Games, Part I: Adventure",
    "link": "https://technicshistory.com/2025/12/13/the-rise-of-computer-games-part-i-adventure/",
    "source": "Hacker News",
    "published": "2025-12-13T20:19:10+00:00",
    "author": "Hacker News",
    "summary": "<a href=\"https://news.ycombinator.com/item?id=46257599\">Comments</a>"
  },
  {
    "title": "VPN location claims don't match real traffic exits",
    "link": "https://ipinfo.io/blog/vpn-location-mismatch-report",
    "source": "Hacker News",
    "published": "2025-12-13T19:46:19+00:00",
    "author": "Hacker News",
    "summary": "<a href=\"https://news.ycombinator.com/item?id=46257339\">Comments</a>"
  },
  {
    "title": "I tried Gleam for Advent of Code",
    "link": "https://blog.tymscar.com/posts/gleamaoc2025/",
    "source": "Hacker News",
    "published": "2025-12-13T17:00:14+00:00",
    "author": "Hacker News",
    "summary": "<a href=\"https://news.ycombinator.com/item?id=46255991\">Comments</a>"
  },
  {
    "title": "Useful patterns for building HTML tools",
    "link": "https://simonwillison.net/2025/Dec/10/html-tools/",
    "source": "Hacker News",
    "published": "2025-12-10T21:08:41+00:00",
    "author": "Hacker News",
    "summary": "<a href=\"https://news.ycombinator.com/item?id=46223882\">Comments</a>"
  },
  {
    "title": "Cat Gap",
    "link": "https://en.wikipedia.org/wiki/Cat_gap",
    "source": "Hacker News",
    "published": "2025-12-10T04:09:04+00:00",
    "author": "Hacker News",
    "summary": "<a href=\"https://news.ycombinator.com/item?id=46213985\">Comments</a>"
  },
  {
    "title": "1 html search engine",
    "link": "https://k8o5.github.io/search",
    "source": "Hacker News",
    "published": "2025-12-09T18:55:15+00:00",
    "author": "Hacker News",
    "summary": "<a href=\"https://news.ycombinator.com/item?id=46208970\">Comments</a>"
  },
  {
    "title": "Using E-Ink tablet as monitor for Linux",
    "link": "https://alavi.me/blog/e-ink-tablet-as-monitor-linux/",
    "source": "Hacker News",
    "published": "2025-12-09T14:10:41+00:00",
    "author": "Hacker News",
    "summary": "<a href=\"https://news.ycombinator.com/item?id=46205089\">Comments</a>"
  },
  {
    "title": "Dhtml Lemmings (2004)",
    "link": "https://www.elizium.nu/scripts/lemmings/index.php",
    "source": "Hacker News",
    "published": "2025-12-08T14:50:47+00:00",
    "author": "Hacker News",
    "summary": "<a href=\"https://news.ycombinator.com/item?id=46192845\">Comments</a>"
  },
  {
    "title": "Cryptids",
    "link": "https://wiki.bbchallenge.org/wiki/Cryptids",
    "source": "Hacker News",
    "published": "2025-12-06T11:48:45+00:00",
    "author": "Hacker News",
    "summary": "<a href=\"https://news.ycombinator.com/item?id=46172586\">Comments</a>"
  }
]